sonus/__init__.py
sonus/__main__.py
sonus/chapterizer.py
sonus/downloader.py
sonus/main.py
sonus-0.6.5.dist-info/LICENSE
sonus-0.6.5.dist-info/METADATA
sonus-0.6.5.dist-info/WHEEL
sonus-0.6.5.dist-info/entry_points.txt
sonus-0.6.5.dist-info/top_level.txt
sonus-0.6.5.dist-info/RECORD
