Metadata-Version: 2.1
Name: sonus
Version: 0.6.5
Summary: Cross-platform OverDrive audiobook client and chapterizer written in Python. 
Home-page: https://github.com/digitalec/sonus
Author: digitalec
License: GPL3
Classifier: License :: OSI Approved :: GNU General Public License v3 (GPLv3)
Classifier: Programming Language :: Python :: 3.6
Classifier: Operating System :: OS Independent
Requires-Python: >=3.6
License-File: LICENSE
Requires-Dist: click~=8.1.7
Requires-Dist: ffmpeg-python~=0.2.0
Requires-Dist: mutagen~=1.47
Requires-Dist: packaging~=24.0
Requires-Dist: requests~=2.31.0
Requires-Dist: tqdm~=4.66.4
Requires-Dist: xmltodict~=0.13.0
